ezname/__init__.py
ezname/cli.py
ezname/core.py
ezname/fixtures.py
ezname/py.typed
ezname-0.1.3.dist-info/METADATA
ezname-0.1.3.dist-info/WHEEL
ezname-0.1.3.dist-info/entry_points.txt
ezname-0.1.3.dist-info/licenses/LICENSE
ezname-0.1.3.dist-info/RECORD
