Metadata-Version: 2.4
Name: ezname
Version: 0.1.3
Summary: A simple tool for generating random, memorable names - better than UUIDs
Author-email: ksterx <kostonerx@gmail.com>
License-File: LICENSE
Requires-Python: >=3.8
